qetpy/__init__.py
qetpy/_version.py
qetpy/core/__init__.py
qetpy/core/_biasparams.py
qetpy/core/_de_pileup.py
qetpy/core/_fitting.py
qetpy/core/_ibis.py
qetpy/core/_noise.py
qetpy/core/_of_1_chan_2_template.py
qetpy/core/_of_1x1.py
qetpy/core/_of_1x2x2.py
qetpy/core/_of_1x3x3.py
qetpy/core/_of_base.py
qetpy/core/_of_nonlin.py
qetpy/core/_of_nsmb.py
qetpy/core/_of_nxm.py
qetpy/core/_of_nxmx2.py
qetpy/core/_of_pileup.py
qetpy/core/didv/__init__.py
qetpy/core/didv/_base_didv.py
qetpy/core/didv/_didv.py
qetpy/core/didv/_didv_priors.py
qetpy/core/didv/_plot_didv.py
qetpy/core/didv/_templates_didv.py
qetpy/core/didv/_uncertainties_didv.py
qetpy/cut/__init__.py
qetpy/cut/_cut.py
qetpy/plotting/__init__.py
qetpy/plotting/_fitting_plotting.py
qetpy/plotting/_ibis_plotting.py
qetpy/plotting/_noise_plotting.py
qetpy/plotting/_of_nsmb_plotting.py
qetpy/sim/__init__.py
qetpy/sim/_sim.py
qetpy/utils/__init__.py
qetpy/utils/_utils.py
qetpy-1.8.4.dist-info/licenses/LICENSE
qetpy-1.8.4.dist-info/METADATA
qetpy-1.8.4.dist-info/WHEEL
qetpy-1.8.4.dist-info/top_level.txt
qetpy-1.8.4.dist-info/RECORD
