Metadata-Version: 2.4
Name: QETpy
Version: 1.8.4
Summary: TES Detector Calibration and Analysis Python Tools
Home-page: https://github.com/spice-herald/QETpy
Author: Samuel Watkins, Caleb Fink
Author-email: samwatkins@berkeley.edu, cwfink@berkeley.edu
Maintainer: Bruno Serfass
Maintainer-email: serfass@berkeley.edu
License-File: LICENSE
Requires-Dist: numpy
Requires-Dist: scipy
Requires-Dist: matplotlib
Requires-Dist: iminuit>=2
Requires-Dist: sympy
Requires-Dist: astropy
Requires-Dist: pandas
Requires-Dist: packaging
Dynamic: author
Dynamic: author-email
Dynamic: description
Dynamic: description-content-type
Dynamic: home-page
Dynamic: license-file
Dynamic: maintainer
Dynamic: maintainer-email
Dynamic: requires-dist
Dynamic: summary
